pycomcigan/__init__.py
pycomcigan/search_school.py
pycomcigan/timetable.py
pycomcigan-1.3.0.dist-info/LICENSE
pycomcigan-1.3.0.dist-info/METADATA
pycomcigan-1.3.0.dist-info/WHEEL
pycomcigan-1.3.0.dist-info/top_level.txt
pycomcigan-1.3.0.dist-info/RECORD
