Metadata-Version: 2.1
Name: pycomcigan
Version: 1.3.0
Summary: 컴시간알리미 시간표 파싱 라이브러리입니다.
Home-page: https://github.com/hegelty/pycomcigan
Author: hegelty
Author-email: skxodid0305@gmail.com
Classifier: Programming Language :: Python :: 3
Classifier: License :: OSI Approved :: MIT License
Classifier: Operating System :: OS Independent
Requires-Python: >=3.9
License-File: LICENSE
Requires-Dist: requests
Requires-Dist: beautifulsoup4
Requires-Dist: urllib3
